traffisim/__init__.py
traffisim/analyzer.py
traffisim/intersection.py
traffisim/models.py
traffisim/rendering.py
traffisim/run.py
traffisim/utils.py
TraffiSim-0.1.1.dist-info/LICENSE
TraffiSim-0.1.1.dist-info/METADATA
TraffiSim-0.1.1.dist-info/WHEEL
TraffiSim-0.1.1.dist-info/entry_points.txt
TraffiSim-0.1.1.dist-info/top_level.txt
TraffiSim-0.1.1.dist-info/RECORD
